spectra/__init__.py
spectra/__main__.py
spectra/bin/spectra_solver
spectra/bin/spectra_solver_nompi
spectra/src/common.js
spectra/src/constants.js
spectra/src/guicomps.js
spectra/src/index.html
spectra/src/launch_solver.js
spectra/src/main.js
spectra/src/newplot.html
spectra/src/newplot.js
spectra/src/objconverter.js
spectra/src/postprocess.js
spectra/src/preprocess.js
spectra/src/prmconverter.js
spectra/src/pythonui.js
spectra/src/spectra.css
spectra/src/spectra.html
spectra/src/spectra_solver.worker.js
spectra/src/spectra_solver_debug.worker.js
spectra/src/updategui.js
spectra/src/css/bootstrap-grid.css
spectra/src/css/bootstrap-grid.css.map
spectra/src/css/bootstrap-grid.min.css
spectra/src/css/bootstrap-grid.min.css.map
spectra/src/css/bootstrap-grid.rtl.css
spectra/src/css/bootstrap-grid.rtl.css.map
spectra/src/css/bootstrap-grid.rtl.min.css
spectra/src/css/bootstrap-grid.rtl.min.css.map
spectra/src/css/bootstrap-reboot.css
spectra/src/css/bootstrap-reboot.css.map
spectra/src/css/bootstrap-reboot.min.css
spectra/src/css/bootstrap-reboot.min.css.map
spectra/src/css/bootstrap-reboot.rtl.css
spectra/src/css/bootstrap-reboot.rtl.css.map
spectra/src/css/bootstrap-reboot.rtl.min.css
spectra/src/css/bootstrap-reboot.rtl.min.css.map
spectra/src/css/bootstrap-utilities.css
spectra/src/css/bootstrap-utilities.css.map
spectra/src/css/bootstrap-utilities.min.css
spectra/src/css/bootstrap-utilities.min.css.map
spectra/src/css/bootstrap-utilities.rtl.css
spectra/src/css/bootstrap-utilities.rtl.css.map
spectra/src/css/bootstrap-utilities.rtl.min.css
spectra/src/css/bootstrap-utilities.rtl.min.css.map
spectra/src/css/bootstrap.css
spectra/src/css/bootstrap.css.map
spectra/src/css/bootstrap.min.css
spectra/src/css/bootstrap.min.css.map
spectra/src/css/bootstrap.rtl.css
spectra/src/css/bootstrap.rtl.css.map
spectra/src/css/bootstrap.rtl.min.css
spectra/src/css/bootstrap.rtl.min.css.map
spectra/src/help/BMsetup.png
spectra/src/help/accuracy.png
spectra/src/help/editmaterial.png
spectra_ui-12.1.4.0.dist-info/METADATA
spectra_ui-12.1.4.0.dist-info/WHEEL
spectra_ui-12.1.4.0.dist-info/top_level.txt
spectra_ui-12.1.4.0.dist-info/RECORD
